{
    "Kitap": {
        "0": ["Gece Yar\u0131s\u0131 K\u00fct\u00fcphanesi", "  Matt Haig", " 58,96"],
        "1": ["Atomik Al\u0131\u015fkanl\u0131klar", "  James Clear", " 74,25"],
        "2": ["Uzaya Giden Tren", "  Mert Ar\u0131k", " 27,52"],
        "3": ["Bir A\u015fk Masal\u0131", "  Ahmet \u00dcmit", " 28,94"],
        "4": ["\u015eeker Portakal\u0131 (Ciltsiz)", "  Jose Mauro De Vasconcelos", " 43,19"],
        "5": ["Simyac\u0131 (Ciltsiz)", "  Paulo Coelho", " 42,44"],
        "6": ["Pal Soka\u011f\u0131 \u00c7ocuklar\u0131", "  Ferenc Molnar", " 22,00"],
        "7": ["Var m\u0131s\u0131n? & G\u00fc\u00e7l\u00fc Bir Ya\u015fam \u0130\u00e7in \u00d6neriler", "  Do\u011fan C\u00fccelo\u011flu", " 52,37"],
        "8": ["\u0130nsan\u0131n Anlam Aray\u0131\u015f\u0131", "  Viktor Emil Frankl", " 65,48"],
        "9": ["\u00c7eyiz", "  Hatice K\u00fcbra Tongar", " 54,00"],
        "10": ["\u0130nsanl\u0131\u011f\u0131m\u0131 Yitirirken", "  Osamu Dazai", " 22,66"],
        "11": ["Ya\u015famak", "  Yu Hua ", " 44,85"],
        "12": ["Veronika \u00d6lmek \u0130stiyor", "  Paulo Coelho", " 60,00"],
        "13": ["Benim Z\u00fcrafam U\u00e7abilir", "  Mert Ar\u0131k", " 34,01"],
        "14": ["\u0130nsan Olmak", "  Engin Ge\u00e7tan", " 58,33"],
        "15": ["O Bir Rol Model", "  Brad Cohen", " 58,50"],
        "16": ["\u00d6zg\u00fcven for Dummies ", "  Lisa Wysocky", " 78,00"],
        "17": ["Tasavvufun Alt\u0131n \u00c7a\u011f\u0131 & Konevi ve Takip\u00e7ileri", "  Kate Burton", " 117,98"],
        "18": ["Veba -  K\u0131sa Bir Giri\u015f", "  Brinley Platts", " 65,00"],
        "19": ["Kapital Ve \u0130deoloji ", "  Ekrem Demirli", " 143,00"],
        "20": ["Nereden \u00c7\u0131kt\u0131 Bu \u00c7ocuk?", "  Paul Slack", " 37,35"],
        "21": ["Do\u011fal Afetler ve Afet Y\u00f6netimi (EMDAT Kriterlerine G\u00f6re)", "  Thomas Piketty", " 50,70"],
        "22": ["Do\u011fa", "  \u0130lknur \u00d6zdemir", " 95,91"],
        "23": ["Ger\u00e7ek Dostlar", "  R\u00fc\u015ft\u00fc Ilgar", " 171,60"],
        "24": ["T\u00fcrkiye T\u00fcrk\u00e7esi Grameri  & Kelime Gruplar\u0131 ve C\u00fcmle Bilgisi", "  Ralph Waldo Emerson", " 51,58"],
        "25": ["A\u015fk Peygamberi", "  Shannon Hale", " 71,50"],
        "26": ["Osmanl\u0131 \u015eehri & \u0130nsan, Mekan ve Be\u015fer\u00ee M\u00fcnasebetler", "  Leuyen Pham", " 20,80"],
        "27": ["Tek Ba\u015f\u0131ma Uyuyorum", "  \u015eahap Bulak", " 92,28"],
        "28": ["Sava\u015f ve Ordu: Ordu Bilgisi", "  Semiha Cemal", " 48,00"]
    }
}